setup.py
streamingzip/__init__.py
streamingzip/__main__.py
streamingzip.egg-info/PKG-INFO
streamingzip.egg-info/SOURCES.txt
streamingzip.egg-info/dependency_links.txt
streamingzip.egg-info/top_level.txt
tests/__init__.py
tests/test_streaming_zip.py