Metadata-Version: 1.0
Name: streamingzip
Version: 0.0.1
Summary: A function to gzip an input file.
Home-page: https://github.com/sujaymansingh/streamingzip
Author: Sujay Mansingh
Author-email: sujay.mansingh@gmail.com
License: LICENSE.txt
Platform: UNKNOWN
